sm02eveldc/__init__.py
sm02eveldc/__main__.py
sm02eveldc-1.2.dist-info/LICENSE
sm02eveldc-1.2.dist-info/METADATA
sm02eveldc-1.2.dist-info/WHEEL
sm02eveldc-1.2.dist-info/top_level.txt
sm02eveldc-1.2.dist-info/RECORD
