Metadata-Version: 2.1
Name: sm02eveldc
Version: 1.2
Summary: evel sh file encoding decoding script
Home-page: https://github.com/pypa/sm02eveldc
Author: Simplehacker1 , Simplehacker01 , Simplehacker02, sm02present
Author-email: rajnikantmahato@gmail.com
License: UNKNOWN
Project-URL: Bug Tracker, https://github.com/pypa/sm02eveldc/issues
Platform: UNKNOWN
Classifier: Programming Language :: Python :: 3
Classifier: Programming Language :: Python :: 3.5
Classifier: Programming Language :: Python :: 3.7
Classifier: License :: OSI Approved :: MIT License
Classifier: Operating System :: OS Independent
Requires-Python: >=3.5
License-File: LICENSE
